[
  {
    "name": "FFB900",
    "hex": "FFB900",
    "r": 255,
    "g": 185,
    "b": 0
  },
  {
    "name": "E74856",
    "hex": "E74856",
    "r": 231,
    "g": 72,
    "b": 86
  },
  {
    "name": "0078D7",
    "hex": "0078D7",
    "r": 0,
    "g": 120,
    "b": 215
  },
  {
    "name": "0099BC",
    "hex": "0099BC",
    "r": 0,
    "g": 153,
    "b": 188
  },
  {
    "name": "7A7574",
    "hex": "7A7574",
    "r": 122,
    "g": 117,
    "b": 116
  },
  {
    "name": "767676",
    "hex": "767676",
    "r": 118,
    "g": 118,
    "b": 118
  },
  {
    "name": "FF8C00",
    "hex": "FF8C00",
    "r": 255,
    "g": 140,
    "b": 0
  },
  {
    "name": "E81123",
    "hex": "E81123",
    "r": 232,
    "g": 17,
    "b": 35
  },
  {
    "name": "0063B1",
    "hex": "0063B1",
    "r": 0,
    "g": 99,
    "b": 177
  },
  {
    "name": "2D7D9A",
    "hex": "2D7D9A",
    "r": 45,
    "g": 125,
    "b": 154
  },
  {
    "name": "5D5A58",
    "hex": "5D5A58",
    "r": 93,
    "g": 90,
    "b": 88
  },
  {
    "name": "4C4A48",
    "hex": "4C4A48",
    "r": 76,
    "g": 74,
    "b": 72
  },
  {
    "name": "F7630C",
    "hex": "F7630C",
    "r": 247,
    "g": 99,
    "b": 12
  },
  {
    "name": "EA005E",
    "hex": "EA005E",
    "r": 234,
    "g": 0,
    "b": 94
  },
  {
    "name": "8E8CD8",
    "hex": "8E8CD8",
    "r": 142,
    "g": 140,
    "b": 216
  },
  {
    "name": "00B7C3",
    "hex": "00B7C3",
    "r": 0,
    "g": 183,
    "b": 195
  },
  {
    "name": "68768A",
    "hex": "68768A",
    "r": 104,
    "g": 118,
    "b": 138
  },
  {
    "name": "69797E",
    "hex": "69797E",
    "r": 105,
    "g": 121,
    "b": 126
  },
  {
    "name": "CA5010",
    "hex": "CA5010",
    "r": 202,
    "g": 80,
    "b": 16
  },
  {
    "name": "C30052",
    "hex": "C30052",
    "r": 195,
    "g": 0,
    "b": 82
  },
  {
    "name": "6B69D6",
    "hex": "6B69D6",
    "r": 107,
    "g": 105,
    "b": 214
  },
  {
    "name": "038387",
    "hex": "038387",
    "r": 3,
    "g": 131,
    "b": 135
  },
  {
    "name": "515C6B",
    "hex": "515C6B",
    "r": 81,
    "g": 92,
    "b": 107
  },
  {
    "name": "4A5459",
    "hex": "4A5459",
    "r": 74,
    "g": 84,
    "b": 89
  },
  {
    "name": "DA3B01",
    "hex": "DA3B01",
    "r": 218,
    "g": 59,
    "b": 1
  },
  {
    "name": "E3008C",
    "hex": "E3008C",
    "r": 227,
    "g": 0,
    "b": 140
  },
  {
    "name": "8764B8",
    "hex": "8764B8",
    "r": 135,
    "g": 100,
    "b": 184
  },
  {
    "name": "00B294",
    "hex": "00B294",
    "r": 0,
    "g": 178,
    "b": 148
  },
  {
    "name": "567C73",
    "hex": "567C73",
    "r": 86,
    "g": 124,
    "b": 115
  },
  {
    "name": "647C64",
    "hex": "647C64",
    "r": 100,
    "g": 124,
    "b": 100
  },
  {
    "name": "EF6950",
    "hex": "EF6950",
    "r": 239,
    "g": 105,
    "b": 80
  },
  {
    "name": "BF0077",
    "hex": "BF0077",
    "r": 191,
    "g": 0,
    "b": 119
  },
  {
    "name": "744DA9",
    "hex": "744DA9",
    "r": 116,
    "g": 77,
    "b": 169
  },
  {
    "name": "018574",
    "hex": "018574",
    "r": 1,
    "g": 133,
    "b": 116
  },
  {
    "name": "486860",
    "hex": "486860",
    "r": 72,
    "g": 104,
    "b": 96
  },
  {
    "name": "525E54",
    "hex": "525E54",
    "r": 82,
    "g": 94,
    "b": 84
  },
  {
    "name": "D13438",
    "hex": "D13438",
    "r": 209,
    "g": 52,
    "b": 56
  },
  {
    "name": "C239B3",
    "hex": "C239B3",
    "r": 194,
    "g": 57,
    "b": 179
  },
  {
    "name": "B146C2",
    "hex": "B146C2",
    "r": 177,
    "g": 70,
    "b": 194
  },
  {
    "name": "00CC6A",
    "hex": "00CC6A",
    "r": 0,
    "g": 204,
    "b": 106
  },
  {
    "name": "498205",
    "hex": "498205",
    "r": 73,
    "g": 130,
    "b": 5
  },
  {
    "name": "847545",
    "hex": "847545",
    "r": 132,
    "g": 117,
    "b": 69
  },
  {
    "name": "FF4343",
    "hex": "FF4343",
    "r": 255,
    "g": 67,
    "b": 67
  },
  {
    "name": "9A0089",
    "hex": "9A0089",
    "r": 154,
    "g": 0,
    "b": 137
  },
  {
    "name": "881798",
    "hex": "881798",
    "r": 136,
    "g": 23,
    "b": 152
  },
  {
    "name": "10893E",
    "hex": "10893E",
    "r": 16,
    "g": 137,
    "b": 62
  },
  {
    "name": "107C10",
    "hex": "107C10",
    "r": 16,
    "g": 124,
    "b": 16
  },
  {
    "name": "7E735F",
    "hex": "7E735F",
    "r": 126,
    "g": 115,
    "b": 95
  }
]
